dromi/__init__.py
dromi/array_utils.py
dromi/mutual_information.py
dromi/similarities.py
dromi/utils.py
dromi-0.0.19.dist-info/licenses/LICENSE.md
dromi-0.0.19.dist-info/METADATA
dromi-0.0.19.dist-info/WHEEL
dromi-0.0.19.dist-info/top_level.txt
dromi-0.0.19.dist-info/RECORD
